<?xml version="1.0" encoding="UTF-8"?>
<objects serializationModel="Studio.02.02.00">
	<object class="AudioFile" id="{144e7815-176d-4022-94ca-781e513a4e3f}">
		<property name="assetPath">
			<value>New Day Prompt.wav</value>
		</property>
		<property name="frequencyInKHz">
			<value>48</value>
		</property>
		<property name="channelCount">
			<value>2</value>
		</property>
		<property name="length">
			<value>2.7873749999999999</value>
		</property>
		<relationship name="masterAssetFolder">
			<destination>{82505715-e88c-4504-b27f-832d272b23d4}</destination>
		</relationship>
	</object>
</objects>
